{
    "product": {
        "name": "SmartWatch",
        "description": "Pulseira loop esportiva",
        "price": 499.99,

        "variations": [
            {
                "name": "Celeste", 
                "color": [
                    {
                        "src": "data/products/1/color.png"
                    }
                ],
                "images": [
                    {
                        "src": "data/products/1/images/0.png"
                    },

                    {
                        "src": "data/products/1/images/1.png"
                    },

                    {
                        "src": "data/products/1/images/2.png"
                    }
                ]
            },

            {
                "name": "Rosa", 
                "color": [
                    {
                        "src": "data/products/2/color.png"
                    }
                ],
                "images": [
                    {
                        "src": "data/products/1/images/0.png"
                    },

                    {
                        "src": "data/products/1/images/1.png"
                    },

                    {
                        "src": "data/products/1/images/2.png"
                    }
                ]
            },


            {
                "name": "Estelar", 
                "color": [
                    {
                        "src": "data/products/3/color.png"
                    }
                ],
                "images": [
                    {
                        "src": "data/products/3/images/0.png"
                    },

                    {
                        "src": "data/products/3/images/1.png"
                    },

                    {
                        "src": "data/products/3/images/2.png"
                    }
                ]
            }
        ]
    }
}